setup.py
pylightwaverf/__init__.py
pylightwaverf/pylightwaverf.py
pylightwaverf.egg-info/PKG-INFO
pylightwaverf.egg-info/SOURCES.txt
pylightwaverf.egg-info/dependency_links.txt
pylightwaverf.egg-info/not-zip-safe
pylightwaverf.egg-info/top_level.txt