Metadata-Version: 1.0
Name: pylightwaverf
Version: 0.1
Summary: Python library for communication with LightWaveRF products (via the WiFi Link)
Home-page: https://github.com/r4abigman/pylightwaverf
Author: Andy Raines
Author-email: UNKNOWN
License: MIT
Platform: UNKNOWN
